itswu/alex/__init__.py
itswu/alex/__main__.py
itswu/alex/async_map.py
itswu/alex/py.typed
itswu.alex-0.0.5.dist-info/METADATA
itswu.alex-0.0.5.dist-info/WHEEL
itswu.alex-0.0.5.dist-info/entry_points.txt
itswu.alex-0.0.5.dist-info/top_level.txt
itswu.alex-0.0.5.dist-info/RECORD
