Metadata-Version: 2.1
Name: itswu.alex
Version: 0.0.5
Summary: A package of utilities.
Author-email: Alex Wu <itswu.alex@gmail.com>
Project-URL: Homepage, https://github.com/wuisawesome/itswu
Project-URL: Issues, https://github.com/wuisawesome/itswu/issues
Classifier: Programming Language :: Python :: 3
Classifier: Operating System :: OS Independent
Requires-Python: >=3.8
